{
  "attrs": [
    {
      "name": "value",
      "sample": "wheel-blocks",
      "type": "Array",
      "desc": "Data source obtained during service invoking.",
      "defaultValue": ""
    },
    {
      "name": "init-blocks",
      "sample": "wheel-blocks",
      "type": "Number",
      "desc": "Number of blocks to be displayed initially.",
      "defaultValue": ""
    },
    {
      "name": "wheel-blocks",
      "sample": "wheel-blocks",
      "type": "Number",
      "desc": "Number of scrolling blocks when the mouse wheel is scrolled up or down.",
      "defaultValue": "The default value of this attribute is 1"
    },
    {
      "name": "tag",
      "sample": "custom-tag",
      "type": "String",
      "desc": "Setting the Dom Label of a Component",
      "defaultValue": "The default value of this attribute is ul."
    },
    {
      "name": "sub-tag",
      "sample": "custom-tag",
      "type": "String",
      "desc": "Setting the Dom Label of a Component",
      "defaultValue": "The default value of this attribute is li"
    }
  ],
  "slots": [
    {
      "name": "default",
      "sample": "custom-content",
      "type": "",
      "desc": "Default scope slot",
      "defaultValue": ""
    }
  ],
  "events": [
    {
      "name": "before-click",
      "sample": "slide-bar-events",
      "type": "Function(value)",
      "desc": "Event triggered before a user swipes the screen. event: Native event",
      "defaultValue": ""
    },
    {
      "name": "click",
      "sample": "slide-bar-events",
      "type": "Function(data, index)",
      "desc": "Sliding block click event; data: data of the clicked slider, index: index value of the clicked slider",
      "defaultValue": ""
    }
  ]
}