{
  "attrs": [
    {
      "name": "disabled",
      "sample": "dynamic-disable",
      "type": "Boolean",
      "desc": "Disable",
      "defaultValue": "The default value of this attribute is false."
    },
    {
      "name": "false-value",
      "sample": "custom-true-false-value",
      "type": "Boolean , String , Number",
      "desc": "Value when switch is disabled",
      "defaultValue": "The default value of this attribute is false."
    },
    {
      "name": "true-value",
      "sample": "custom-true-false-value",
      "type": "Boolean , String , Number",
      "desc": "Value when switch is enabled",
      "defaultValue": "The default value of this attribute is true."
    },
    {
      "name": "show-text",
      "sample": "custom-open-close",
      "type": "Boolean",
      "desc": "Switch whether to display the text in the content.",
      "defaultValue": "The default value of this attribute is false."
    },
    {
      "name": "mini",
      "sample": "mini-mode",
      "type": "Boolean",
      "desc": "Sets whether to display in mini mode. In mini mode, the content of the slot is not displayed.",
      "defaultValue": "The default value of this attribute is false."
    },
    {
      "name": "modelValue / v-model",
      "sample": "basic-usage",
      "type": "Boolean , String , Number",
      "desc": "Bound Value",
      "defaultValue": ""
    }
  ],
  "slots": [
    {
      "name": "open",
      "sample": "custom-open-close",
      "type": "",
      "desc": "Enable Content",
      "defaultValue": ""
    },
    {
      "name": "close",
      "sample": "custom-open-close",
      "type": "",
      "desc": "Close Content",
      "defaultValue": ""
    }
  ],
  "events": [
    {
      "name": "change",
      "sample": "enent",
      "type": "",
      "desc": "Callback function for switch changes",
      "defaultValue": ""
    }
  ]
}
